{
    ".": "3.16.1",
    "packages/api": "3.4.3",
    "packages/chart": "3.5.3",
    "packages/codemirror": "3.6.3",
    "packages/common": "3.5.3",
    "packages/comms": "3.12.1",
    "packages/composite": "3.4.3",
    "packages/dataflow": "9.6.0",
    "packages/ddl-shim": "3.2.2",
    "packages/dgrid": "3.5.3",
    "packages/dgrid-shim": "3.3.1",
    "packages/dgrid2": "3.5.1",
    "packages/eclwatch": "3.5.3",
    "packages/esbuild-plugins": "1.7.0",
    "packages/form": "3.3.3",
    "packages/graph": "3.5.3",
    "packages/html": "3.3.3",
    "packages/layout": "3.4.3",
    "packages/map": "3.4.3",
    "packages/markdown-it-plugins": "1.5.2",
    "packages/observablehq-compiler": "3.7.0",
    "packages/other": "3.4.3",
    "packages/phosphor": "3.4.1",
    "packages/react": "3.4.3",
    "packages/timeline": "3.2.3",
    "packages/tree": "3.2.3",
    "packages/util": "3.4.3"
}